Workbook

Sheet Start here
B2: Utah construction market data
B3: Data package for Ethan Hall • collected October 1, 2026
B5: Project | C5: Where Should a Utah Construction Supplier Expand? An independent case study for a hypothetical supplier.
B6: Coverage | C6: All 29 Utah counties; 2021–2025 analysis, with 2020 retained as a baseline for 2021 growth.
B7: Start with | C7: County annual: 174 county-year rows. Filter Period role to analysis for the five-year project.
B8: Go deeper | C8: By structure: 696 rows covering 1-unit, 2-unit, 3–4-unit and 5+ unit residential buildings.
B9: Measures | C9: Buildings, housing units and permit valuation. A building can contain many units. These are not counts of permit documents.
B10: Source trace | C10: Match Source ID to Sources. Source line points to the exact line in the unchanged original text file, including headers.
B11: What passed | C11: 19 data checks, including 144 county-to-state comparisons. Counts match exactly; values agree within $500 per state category.
B12: Avoid double counting | C12: Estimated values include reported data and imputation. Never add estimated and reported-only measures.
B13: 2023 coverage change | C13: Census moved from the fixed 2014 permit-office universe to annual updates. Interpret growth across 2022–2023 with that caveat.
B14: Dollar scale | C14: County valuations are whole nominal USD. State control files are in thousands; the package converts them for reconciliation.
B15: Scope limit | C15: The data describes authorizations of new private residential construction. It does not establish starts, completions, sales or supplier profits.
B16: Imputation | C16: Imputed unit share = (estimated units − reported units) / estimated units. Blank if the denominator is zero; not a response rate.
... B18: Next analysis | C18: Compare market size, yearly change, structure mix and annual consistency. Keep rankings and recommendations separate from these source data.
B20: Open the Data Guide for source notes, file instructions and project boundaries.

Sheet County annual
A1: Utah residential construction | County annual data
A2: 2021–2025 analysis • 2020 baseline • estimates include Census imputation • Sources and Dictionary explain the fields
A5: Year | B5: County | C5: County FIPS | D5: 1-unit units | E5: 2-unit units | F5: 3–4-unit units | G5: 5+ units | H5: Total units | I5: Multifamily units | J5: Valuation USD | K5: Reported units | L5: Imputed unit share | M5: Period role | N5: Coverage basis | O5: Source ID | P5: Source line
A6: 2020 | B6: Beaver County | C6: 49001 | D6: 38 | E6: 0 | F6: 4 | G6: 0 | H6: =SUM(D6:G6) -> 42 | I6: =SUM(E6:G6) -> 4 | J6: =SUMIFS('By structure'!$G$6:$G$701,'By structure'!$A$6:$A$701,A6,'By structure'!$C$6:$C$701,C6) -> 11814547 | K6: =SUMIFS('By structure'!$H$6:$H$701,'By structure'!$A$6:$A$701,A6,'By structure'!$C$6:$C$701,C6) -> 42 | L6: =IF(H6=0,"",(H6-K6)/H6) -> 0 | M6: baseline | N6: 2014 fixed universe | O6: BPS-CO-2020 | P6: 2675
A7: 2020 | B7: Box Elder County | C7: 49003 | D7: 381 | E7: 4 | F7: 60 | G7: 88 | H7: =SUM(D7:G7) -> 533 | I7: =SUM(E7:G7) -> 152 | J7: =SUMIFS('By structure'!$G$6:$G$701,'By structure'!$A$6:$A$701,A7,'By structure'!$C$6:$C$701,C7) -> 92714260 | K7: =SUMIFS('By structure'!$H$6:$H$701,'By structure'!$A$6:$A$701,A7,'By structure'!$C$6:$C$701,C7) -> 384 | L7: =IF(H7=0,"",(H7-K7)/H7) -> 0.27954972 | M7: baseline | N7: 2014 fixed universe | O7: BPS-CO-2020 | P7: 2676
A8: 2020 | B8: Cache County | C8: 49005 | D8: 987 | E8: 6 | F8: 31 | G8: 586 | H8: =SUM(D8:G8) -> 1610 | I8: =SUM(E8:G8) -> 623 | J8: =SUMIFS('By structure'!$G$6:$G$701,'By structure'!$A$6:$A$701,A8,'By structure'!$C$6:$C$701,C8) -> 321528306 | K8: =SUMIFS('By structure'!$H$6:$H$701,'By structure'!$A$6:$A$701,A8,'By structure'!$C$6:$C$701,C8) -> 1610 | L8: =IF(H8=0,"",(H8-K8)/H8) -> 0 | M8: baseline | N8: 2014 fixed universe | O8: BPS-CO-2020 | P8: 2677
A9: 2020 | B9: Carbon County | C9: 49007 | D9: 21 | E9: 2 | F9: 0 | G9: 0 | H9: =SUM(D9:G9) -> 23 | I9: =SUM(E9:G9) -> 2 | J9: =SUMIFS('By structure'!$G$6:$G$701,'By structure'!$A$6:$A$701,A9,'By structure'!$C$6:$C$701,C9) -> 6817438 | K9: =SUMIFS('By structure'!$H$6:$H$701,'By structure'!$A$6:$A$701,A9,'By structure'!$C$6:$C$701,C9) -> 23 | L9: =IF(H9=0,"",(H9-K9)/H9) -> 0 | M9: baseline | N9: 2014 fixed universe | O9: BPS-CO-2020 | P9: 2678
A10: 2020 | B10: Daggett County | C10: 49009 | D10: 9 | E10: 0 | F10: 0 | G10: 0 | H10: =SUM(D10:G10) -> 9 | I10: =SUM(E10:G10) -> 0 | J10: =SUMIFS('By structure'!$G$6:$G$701,'By structure'!$A$6:$A$701,A10,'By structure'!$C$6:$C$701,C10) -> 2258152 | K10: =SUMIFS('By structure'!$H$6:$H$701,'By structure'!$A$6:$A$701,A10,'By structure'!$C$6:$C$701,C10) -> 4 | L10: =IF(H10=0,"",(H10-K10)/H10) -> 0.55555556 | M10: baseline | N10: 2014 fixed universe | O10: BPS-CO-2020 | P10: 2679
A11: 2020 | B11: Davis County | C11: 49011 | D11: 1946 | E11: 12 | F11: 25 | G11: 434 | H11: =SUM(D11:G11) -> 2417 | I11: =SUM(E11:G11) -> 471 | J11: =SUMIFS('By structure'!$G$6:$G$701,'By structure'!$A$6:$A$701,A11,'By structure'!$C$6:$C$701,C11) -> 603236927 | K11: =SUMIFS('By structure'!$H$6:$H$701,'By structure'!$A$6:$A$701,A11,'By structure'!$C$6:$C$701,C11) -> 2417 | L11: =IF(H11=0,"",(H11-K11)/H11) -> 0 | M11: baseline | N11: 2014 fixed universe | O11: BPS-CO-2020 | P11: 2680
A12: 2020 | B12: Duchesne County | C12: 49013 | D12: 101 | E12: 0 | F12: 4 | G12: 0 | H12: =SUM(D12:G12) -> 105 | I12: =SUM(E12:G12) -> 4 | J12: =SUMIFS('By structure'!$G$6:$G$701,'By structure'!$A$6:$A$701,A12,'By structure'!$C$6:$C$701,C12) -> 24105274 | K12: =SUMIFS('By structure'!$H$6:$H$701,'By structure'!$A$6:$A$701,A12,'By structure'!$C$6:$C$701,C12) -> 54 | L12: =IF(H12=0,"",(H12-K12)/H12) -> 0.48571429 | M12: baseline | N12: 2014 fixed universe | O12: BPS-CO-2020 | P12: 2681
A13: 2020 | B13: Emery County | C13: 49015 | D13: 7 | E13: 0 | F13: 0 | G13: 0 | H13: =SUM(D13:G13) -> 7 | I13: =SUM(E13:G13) -> 0 | J13: =SUMIFS('By structure'!$G$6:$G$701,'By structure'!$A$6:$A$701,A13,'By structure'!$C$6:$C$701,C13) -> 1628900 | K13: =SUMIFS('By structure'!$H$6:$H$701,'By structure'!$A$6:$A$701,A13,'By structure'!$C$6:$C$701,C13) -> 0 | L13: =IF(H13=0,"",(H13-K13)/H13) -> 1 | M13: baseline | N13: 2014 fixed universe | O13: BPS-CO-2020 | P13: 2682
A14: 2020 | B14: Garfield County | C14: 49017 | D14: 58 | E14: 0 | F14: 0 | G14: 0 | H14: =SUM(D14:G14) -> 58 | I14: =SUM(E14:G14) -> 0 | J14: =SUMIFS('By structure'!$G$6:$G$701,'By structure'!$A$6:$A$701,A14,'By structure'!$C$6:$C$701,C14) -> 12107805 | K14: =SUMIFS('By structure'!$H$6:$H$701,'By structure'!$A$6:$A$701,A14,'By structure'!$C$6:$C$701,C14) -> 58 | L14: =IF(H14=0,"",(H14-K14)/H14) -> 0 | M14: baseline | N14: 2014 fixed universe | O14: BPS-CO-2020 | P14: 2683
A15: 2020 | B15: Grand County | C15: 49019 | D15: 71 | E15: 12 | F15: 24 | G15: 0 | H15: =SUM(D15:G15) -> 107 | I15: =SUM(E15:G15) -> 36 | J15: =SUMIFS('By structure'!$G$6:$G$701,'By structure'!$A$6:$A$701,A15,'By structure'!$C$6:$C$701,C15) -> 22796380 | K15: =SUMIFS('By structure'!$H$6:$H$701,'By structure'!$A$6:$A$701,A15,'By structure'!$C$6:$C$701,C15) -> 107 | L15: =IF(H15=0,"",(H15-K15)/H15) -> 0 | M15: baseline | N15: 2014 fixed universe | O15: BPS-CO-2020 | P15: 2684
A16: 2020 | B16: Iron County | C16: 49021 | D16: 473 | E16: 2 | F16: 0 | G16: 39 | H16: =SUM(D16:G16) -> 514 | I16: =SUM(E16:G16) -> 41 | J16: =SUMIFS('By structure'!$G$6:$G$701,'By structure'!$A$6:$A$701,A16,'By structure'!$C$6:$C$701,C16) -> 109378486 | K16: =SUMIFS('By structure'!$H$6:$H$701,'By structure'!$A$6:$A$701,A16,'By structure'!$C$6:$C$701,C16) -> 203 | L16: =IF(H16=0,"",(H16-K16)/H16) -> 0.60505837 | M16: baseline | N16: 2014 fixed universe | O16: BPS-CO-2020 | P16: 2685
A17: 2020 | B17: Juab County | C17: 49023 | D17: 69 | E17: 10 | F17: 4 | G17: 25 | H17: =SUM(D17:G17) -> 108 | I17: =SUM(E17:G17) -> 39 | J17: =SUMIFS('By structure'!$G$6:$G$701,'By structure'!$A$6:$A$701,A17,'By structure'!$C$6:$C$701,C17) -> 28711867 | K17: =SUMIFS('By structure'!$H$6:$H$701,'By structure'!$A$6:$A$701,A17,'By structure'!$C$6:$C$701,C17) -> 92 | L17: =IF(H17=0,"",(H17-K17)/H17) -> 0.14814815 | M17: baseline | N17: 2014 fixed universe | O17: BPS-CO-2020 | P17: 2686
... A179: 2025 | B179: Weber County | C179: 49057 | D179: 813 | E179: 6 | F179: 57 | G179: 614 | H179: =SUM(D179:G179) -> 1490 | I179: =SUM(E179:G179) -> 677 | J179: =SUMIFS('By structure'!$G$6:$G$701,'By structure'!$A$6:$A$701,A179,'By structure'!$C$6:$C$701,C179) -> 442546376 | K179: =SUMIFS('By structure'!$H$6:$H$701,'By structure'!$A$6:$A$701,A179,'By structure'!$C$6:$C$701,C179) -> 845 | L179: =IF(H179=0,"",(H179-K179)/H179) -> 0.43288591 | M179: analysis | N179: annually updated universe | O179: BPS-CO-2025 | P179: 2698

Sheet By structure
A1: Utah residential construction | Structure detail
A2: Four structure types per county and year • estimated measures already include reported data • do not add both blocks
A5: Year | B5: County | C5: County FIPS | D5: Structure type | E5: Est. buildings | F5: Est. units | G5: Est. valuation USD | H5: Reported units | I5: Reported buildings | J5: Reported valuation USD | K5: Source ID | L5: Source line
A6: 2020 | B6: Beaver County | C6: 49001 | D6: 1-unit | E6: 38 | F6: 38 | G6: 11007562 | H6: 38 | I6: 38 | J6: 11007562 | K6: BPS-CO-2020 | L6: 2675
A7: 2020 | B7: Beaver County | C7: 49001 | D7: 2-unit | E7: 0 | F7: 0 | G7: 0 | H7: 0 | I7: 0 | J7: 0 | K7: BPS-CO-2020 | L7: 2675
A8: 2020 | B8: Beaver County | C8: 49001 | D8: 3-4-unit | E8: 1 | F8: 4 | G8: 806985 | H8: 4 | I8: 1 | J8: 806985 | K8: BPS-CO-2020 | L8: 2675
A9: 2020 | B9: Beaver County | C9: 49001 | D9: 5-plus-unit | E9: 0 | F9: 0 | G9: 0 | H9: 0 | I9: 0 | J9: 0 | K9: BPS-CO-2020 | L9: 2675
A10: 2020 | B10: Box Elder County | C10: 49003 | D10: 1-unit | E10: 381 | F10: 381 | G10: 81497548 | H10: 236 | I10: 236 | J10: 46344986 | K10: BPS-CO-2020 | L10: 2676
A11: 2020 | B11: Box Elder County | C11: 49003 | D11: 2-unit | E11: 2 | F11: 4 | G11: 318718 | H11: 4 | I11: 2 | J11: 318718 | K11: BPS-CO-2020 | L11: 2676
A12: 2020 | B12: Box Elder County | C12: 49003 | D12: 3-4-unit | E12: 15 | F12: 60 | G12: 2534906 | H12: 56 | I12: 14 | J12: 2072393 | K12: BPS-CO-2020 | L12: 2676
A13: 2020 | B13: Box Elder County | C13: 49003 | D13: 5-plus-unit | E13: 14 | F13: 88 | G13: 8363088 | H13: 88 | I13: 14 | J13: 8363088 | K13: BPS-CO-2020 | L13: 2676
A14: 2020 | B14: Cache County | C14: 49005 | D14: 1-unit | E14: 987 | F14: 987 | G14: 259620189 | H14: 987 | I14: 987 | J14: 259620189 | K14: BPS-CO-2020 | L14: 2677
A15: 2020 | B15: Cache County | C15: 49005 | D15: 2-unit | E15: 3 | F15: 6 | G15: 1382564 | H15: 6 | I15: 3 | J15: 1382564 | K15: BPS-CO-2020 | L15: 2677
A16: 2020 | B16: Cache County | C16: 49005 | D16: 3-4-unit | E16: 10 | F16: 31 | G16: 5254435 | H16: 31 | I16: 10 | J16: 5254435 | K16: BPS-CO-2020 | L16: 2677
A17: 2020 | B17: Cache County | C17: 49005 | D17: 5-plus-unit | E17: 30 | F17: 586 | G17: 55271118 | H17: 586 | I17: 30 | J17: 55271118 | K17: BPS-CO-2020 | L17: 2677
... A701: 2025 | B701: Weber County | C701: 49057 | D701: 5-plus-unit | E701: 57 | F701: 614 | G701: 114896883 | H701: 272 | I701: 42 | J701: 62117279 | K701: BPS-CO-2025 | L701: 2698

Sheet Sources
A1: Source register | U.S. Census Bureau
A2: Downloaded October 1, 2026 • unchanged originals are included in the package • source IDs connect records to their origin
A5: Source ID | B5: Source title | C5: Original URL | D5: Local snapshot | E5: Retrieved at UTC | F5: SHA-256
A6: BPS-CO-2020 | B6: Census BPS county annual file, 2020 | C6: https://www2.census.gov/econ/bps/County/co2020a.txt | D6: raw/county/co2020a.txt | E6: 46296.835 | F6: 04efba6d3ffecd19340dece9d76d01343f8b97647617c79422c04e227e2d7293
A7: BPS-ST-2020 | B7: Census BPS state annual file, 2020 | C7: https://www2.census.gov/econ/bps/State/st2020a.txt | D7: raw/state/st2020a.txt | E7: 46296.835 | F7: 446533087cb10997e488f081d05a2f04179468a04bd543316c0167763965cfd4
A8: BPS-CO-2021 | B8: Census BPS county annual file, 2021 | C8: https://www2.census.gov/econ/bps/County/co2021a.txt | D8: raw/county/co2021a.txt | E8: 46296.835 | F8: ce2c9aa7b7c036ddbc99d6dc398ddf71e4a0ad0fc2782db883b559ca264f14b6
A9: BPS-ST-2021 | B9: Census BPS state annual file, 2021 | C9: https://www2.census.gov/econ/bps/State/st2021a.txt | D9: raw/state/st2021a.txt | E9: 46296.835 | F9: 82fea768a93c91a702c91727d8dea64d2573f835dc9858b11d0e63a4092c524b
A10: BPS-CO-2022 | B10: Census BPS county annual file, 2022 | C10: https://www2.census.gov/econ/bps/County/co2022a.txt | D10: raw/county/co2022a.txt | E10: 46296.835 | F10: 0a88c16861ede81b04f8785e1c626e772510f33f1de9452f7592d86d308e2b5c
A11: BPS-ST-2022 | B11: Census BPS state annual file, 2022 | C11: https://www2.census.gov/econ/bps/State/st2022a.txt | D11: raw/state/st2022a.txt | E11: 46296.835 | F11: c973dde1f227de2c825ac0ce20b604979291080c7a1f70e9c953bf5a13980790
A12: BPS-CO-2023 | B12: Census BPS county annual file, 2023 | C12: https://www2.census.gov/econ/bps/County/co2023a.txt | D12: raw/county/co2023a.txt | E12: 46296.835 | F12: fab11d759e905ff61838b8dfa41c0f2082e150cad07a20c65ddd620a007aa158
A13: BPS-ST-2023 | B13: Census BPS state annual file, 2023 | C13: https://www2.census.gov/econ/bps/State/st2023a.txt | D13: raw/state/st2023a.txt | E13: 46296.835 | F13: c3915919cc2b58ccb2be6c9e6000f064236aeaa9d032f9352d60c0f484b4a583
A14: BPS-CO-2024 | B14: Census BPS county annual file, 2024 | C14: https://www2.census.gov/econ/bps/County/co2024a.txt | D14: raw/county/co2024a.txt | E14: 46296.835 | F14: a64c2dd19be96c469763c10d637575a584ef16a6878f451bba80c847bcafc8c6
A15: BPS-ST-2024 | B15: Census BPS state annual file, 2024 | C15: https://www2.census.gov/econ/bps/State/st2024a.txt | D15: raw/state/st2024a.txt | E15: 46296.835 | F15: 8dd34fb3bc362a0d6c1e6832161432dd833aff9be49ebebc128335635c59e7d0
A16: BPS-CO-2025 | B16: Census BPS county annual file, 2025 | C16: https://www2.census.gov/econ/bps/County/co2025a.txt | D16: raw/county/co2025a.txt | E16: 46296.835 | F16: 5d523b1ff172c886ee7f2bc770c82c8c5470b5aaaec5f63441a18c621c80b30e
A17: BPS-ST-2025 | B17: Census BPS state annual file, 2025 | C17: https://www2.census.gov/econ/bps/State/st2025a.txt | D17: raw/state/st2025a.txt | E17: 46296.835 | F17: eab29258ada8389b9f469c566eb6eb074cf128aa94c471e89f818a20a4d83afb
... A26: DOC-C404-FORM | B26: C-404 building permits survey sample form | C26: https://www.census.gov/construction/bps/pdf/c404_06142024_sample_final.pdf | D26: sources/c404_sample.pdf | E26: 46296.837 | F26: f419cc2cf6f92772d11ced2ae060f69bdbb60ef80ee55159f68466ee5b94ac9b

Sheet Dictionary
A1: Data dictionary | CSV field definitions
A2: Filter Dataset to see one table • amounts are nominal USD unless explicitly labeled thousand USD • FIPS identifiers are text
A5: Dataset | B5: Field | C5: Data type | D5: Unit | E5: Definition | F5: Source or derivation
A6: county_annual | B6: year | C6: integer | D6: calendar year | E6: Annual period; 2020 is only the growth baseline. | F6: County field 1; state field 1 uses YYYY99.
A7: county_annual | B7: state_fips | C7: text | D7: code | E7: Two-character state identifier; Utah is 49. | F7: County/state field 2.
A8: county_annual | B8: county_fips | C8: text | D8: code | E8: Three-character county identifier; preserve leading zeros. | F8: County field 3.
A9: county_annual | B9: county_fips5 | C9: text | D9: code | E9: Five-character unique county identifier. | F9: state_fips + county_fips; primary-key component.
A10: county_annual | B10: county_name | C10: text | D10: name | E10: Census county name, with leading/trailing spaces removed. | F10: County field 6.
A11: county_annual | B11: single_family_units | C11: integer | D11: count | E11: Units in 1-unit buildings, including qualifying attached homes. | F11: county_by_structure estimated_units for 101.
A12: county_annual | B12: two_unit_units | C12: integer | D12: count | E12: Units in 2-unit buildings. | F12: county_by_structure estimated_units for 103.
A13: county_annual | B13: three_four_unit_units | C13: integer | D13: count | E13: Units in 3-4-unit buildings. | F13: county_by_structure estimated_units for 104.
A14: county_annual | B14: five_plus_unit_units | C14: integer | D14: count | E14: Units in buildings containing at least 5 units. | F14: county_by_structure estimated_units for 105.
A15: county_annual | B15: total_buildings | C15: integer | D15: count | E15: Total estimated residential buildings authorized. | F15: Sum estimated_buildings across all four structure types.
A16: county_annual | B16: total_units | C16: integer | D16: count | E16: Total estimated housing units authorized; includes imputation. | F16: Sum estimated_units across all four structure types.
... A67: utah_state_controls | B67: source_line | C67: integer | D67: line number | E67: One-based physical source line including header rows. | F67: Recorded while parsing original text file.
